SquareMap3-1.0.8.dist-info/DESCRIPTION.rst
SquareMap3-1.0.8.dist-info/METADATA
SquareMap3-1.0.8.dist-info/RECORD
SquareMap3-1.0.8.dist-info/WHEEL
SquareMap3-1.0.8.dist-info/metadata.json
SquareMap3-1.0.8.dist-info/top_level.txt
squaremap/__init__.py
squaremap/_version.py
squaremap/squaremap.py
