Metadata-Version: 2.0
Name: SquareMap3
Version: 1.0.8
Summary: Hierarchic data-visualisation control for wxPython
Home-page: https://launchpad.net/squaremap
Author: Mike C. Fletcher
Author-email: mcfletch@vrplumber.com
License: BSD
Keywords: wxPython,squaremap
Platform: Any
Classifier: License :: OSI Approved :: BSD License
Classifier: Programming Language :: Python
Classifier: Topic :: Software Development :: Libraries :: Python Modules
Classifier: Intended Audience :: Developers
Requires-Dist: wxPython
